beametrics/__init__.py
beametrics/config.py
beametrics/filter.py
beametrics/main.py
beametrics/metrics.py
beametrics/metrics_exporter.py
beametrics/pipeline.py
beametrics-0.3.0.dist-info/METADATA
beametrics-0.3.0.dist-info/WHEEL
beametrics-0.3.0.dist-info/entry_points.txt
beametrics-0.3.0.dist-info/RECORD
